{
  "items": [],
  "rels": {
    "canonical": [
      "https://againstthefuture.net/"
    ],
    "stylesheet": [
      "https://againstthefuture.net/assets/style.css",
      "https://againstthefuture.net/style.css",
      "https://againstthefuture.net/custom.css",
      "https://againstthefuture.net/assets/css/poststats.css"
    ],
    "apple-touch-icon-precomposed": [
      "https://againstthefuture.net/img/apple-touch-icon-144-precomposed.png"
    ],
    "icon": [
      "https://againstthefuture.net/img/favicon.png"
    ],
    "shortcut": [
      "https://againstthefuture.net/img/favicon.png"
    ],
    "alternate": [
      "https://againstthefuture.net/feed.xml",
      "https://againstthefuture.net/podcast.xml",
      "https://againstthefuture.net/feed.json"
    ],
    "EditURI": [
      "https://againstthefuture.net/rsd.xml"
    ],
    "me": [
      "https://micro.blog/jdm"
    ],
    "authorization_endpoint": [
      "https://micro.blog/indieauth/auth"
    ],
    "token_endpoint": [
      "https://micro.blog/indieauth/token"
    ],
    "micropub": [
      "https://micro.blog/micropub"
    ],
    "microsub": [
      "https://micro.blog/microsub"
    ],
    "webmention": [
      "https://micro.blog/webmention"
    ],
    "subscribe": [
      "https://micro.blog/users/follow"
    ],
    "license": [
      "http://creativecommons.org/licenses/by-nc-nd/4.0/"
    ]
  },
  "rel-urls": {
    "https://againstthefuture.net/": {
      "rels": [
        "canonical"
      ]
    },
    "https://againstthefuture.net/assets/style.css": {
      "rels": [
        "stylesheet"
      ]
    },
    "https://againstthefuture.net/style.css": {
      "rels": [
        "stylesheet"
      ]
    },
    "https://againstthefuture.net/custom.css": {
      "rels": [
        "stylesheet"
      ],
      "type": "text/css"
    },
    "https://againstthefuture.net/img/apple-touch-icon-144-precomposed.png": {
      "rels": [
        "apple-touch-icon-precomposed"
      ]
    },
    "https://againstthefuture.net/img/favicon.png": {
      "rels": [
        "icon",
        "shortcut"
      ]
    },
    "https://againstthefuture.net/feed.xml": {
      "rels": [
        "alternate"
      ],
      "title": "Against the Future",
      "type": "application/rss+xml"
    },
    "https://againstthefuture.net/podcast.xml": {
      "rels": [
        "alternate"
      ],
      "title": "Podcast",
      "type": "application/rss+xml"
    },
    "https://againstthefuture.net/feed.json": {
      "rels": [
        "alternate"
      ],
      "title": "Against the Future",
      "type": "application/json"
    },
    "https://againstthefuture.net/rsd.xml": {
      "rels": [
        "EditURI"
      ],
      "type": "application/rsd+xml"
    },
    "https://micro.blog/jdm": {
      "rels": [
        "me"
      ]
    },
    "https://micro.blog/indieauth/auth": {
      "rels": [
        "authorization_endpoint"
      ]
    },
    "https://micro.blog/indieauth/token": {
      "rels": [
        "token_endpoint"
      ]
    },
    "https://micro.blog/micropub": {
      "rels": [
        "micropub"
      ]
    },
    "https://micro.blog/microsub": {
      "rels": [
        "microsub"
      ]
    },
    "https://micro.blog/webmention": {
      "rels": [
        "webmention"
      ]
    },
    "https://micro.blog/users/follow": {
      "rels": [
        "subscribe"
      ]
    },
    "https://againstthefuture.net/assets/css/poststats.css": {
      "rels": [
        "stylesheet"
      ]
    },
    "http://creativecommons.org/licenses/by-nc-nd/4.0/": {
      "rels": [
        "license"
      ]
    }
  }
}