{
  "items": [],
  "rels": {
    "icon": [
      "https://lh5.googleusercontent.com/u-G0lmlf5MOaO9hHEors50uDSmp8WQKH0Di5Yd8Gv2Ze6FKnSDIWRh01MqhxzUXXC5M87E_AK7JJjLEHaa-E60wYNes2jfBG49f3VQP2_BMN1bZe"
    ],
    "stylesheet": [
      "https://fonts.googleapis.com/css?family=Lato%3A300%2C300italic%2C400%2C400italic%2C700%2C700italic&display=swap",
      "https://fonts.googleapis.com/css?family=Google+Sans:400,500|Roboto:300,400,500,700|Source+Code+Pro:400,700&display=swap",
      "https://www.gstatic.com/_/atari/_/ss/k=atari.vw.61bqKzHBQSk.L.X.O/d=1/rs=AGEqA5nbkBDBnjeyVz2WMgUQVhdClUVVGA"
    ]
  },
  "rel-urls": {
    "https://lh5.googleusercontent.com/u-G0lmlf5MOaO9hHEors50uDSmp8WQKH0Di5Yd8Gv2Ze6FKnSDIWRh01MqhxzUXXC5M87E_AK7JJjLEHaa-E60wYNes2jfBG49f3VQP2_BMN1bZe": {
      "rels": [
        "icon"
      ]
    },
    "https://fonts.googleapis.com/css?family=Lato%3A300%2C300italic%2C400%2C400italic%2C700%2C700italic&display=swap": {
      "rels": [
        "stylesheet"
      ]
    },
    "https://fonts.googleapis.com/css?family=Google+Sans:400,500|Roboto:300,400,500,700|Source+Code+Pro:400,700&display=swap": {
      "rels": [
        "stylesheet"
      ]
    },
    "https://www.gstatic.com/_/atari/_/ss/k=atari.vw.61bqKzHBQSk.L.X.O/d=1/rs=AGEqA5nbkBDBnjeyVz2WMgUQVhdClUVVGA": {
      "rels": [
        "stylesheet"
      ]
    }
  }
}