{
  "items": [],
  "rels": {
    "stylesheet": [
      "https://fonts.googleapis.com/css?family=Droid+Serif:400,700",
      "https://fonts.googleapis.com/css?family=Open+Sans:300,700"
    ],
    "me": [
      "https://donoskaro.com/cdn-cgi/l/email-protection#a6cbc3e6c2c9c8c9d5cdc7d4c988c5c9cb",
      "https://twitter.com/donoskaro"
    ]
  },
  "rel-urls": {
    "https://fonts.googleapis.com/css?family=Droid+Serif:400,700": {
      "rels": [
        "stylesheet"
      ],
      "type": "text/css"
    },
    "https://fonts.googleapis.com/css?family=Open+Sans:300,700": {
      "rels": [
        "stylesheet"
      ],
      "type": "text/css"
    },
    "https://donoskaro.com/cdn-cgi/l/email-protection#a6cbc3e6c2c9c8c9d5cdc7d4c988c5c9cb": {
      "rels": [
        "me"
      ],
      "text": "[email protected]"
    },
    "https://twitter.com/donoskaro": {
      "rels": [
        "me"
      ],
      "text": "@donoskaro"
    }
  }
}