{
  "items": [
    {
      "type": [
        "h-card"
      ],
      "properties": {
        "photo": [
          {
            "value": "https://genehack.org/images/genehack.jpg",
            "alt": "Headshot of John taken by Dr. Paris Buttfield-Addison"
          }
        ],
        "url": [
          "https://genehack.org/",
          "https://genehack.org/genehack",
          "https://genehack.blog/",
          "https://twitter.com/genehack",
          "https://mastodon.social/@genehack",
          "https://covid.house/",
          "https://recipes.genehack.org/",
          "https://bandcamp.com/genehack",
          "https://metacpan.org/author/GENEHACK",
          "https://diasp.org/people/4d287f11ec26e226f7000384",
          "https://genehack.dreamwidth.org/",
          "https://www.facebook.com/genehack",
          "https://www.flickr.com/photos/genehack/",
          "ircs://chat.freenode.net:6697/genehack,isnick",
          "https://github.com/genehack",
          "https://gitlab.com/genehack",
          "https://www.goodreads.com/user/show/2982810-john-anderson",
          "https://keybase.io/genehack",
          "https://www.instagram.com/genehack/",
          "https://www.linkedin.com/in/johnsjanderson/",
          "https://mastodon.social/@genehack",
          "https://www.metafilter.com/user/13976",
          "http://genehack.newsblur.com/",
          "https://www.npmjs.com/~genehack",
          "https://opencollective.com/genehack",
          "https://www.patreon.com/genehack/",
          "https://pinboard.in/u:genehack",
          "https://www.pinterest.com/genehack/",
          "https://www.reddit.com/user/genehack/",
          "https://stackexchange.com/users/17710/genehack",
          "https://steamcommunity.com/id/genehack/",
          "https://beta.thestorygraph.com/profile/ff04ef58-368d-4617-9188-727c86bc3228",
          "https://twitter.com/genehack",
          "https://www.tumblr.com/blog/tumblrwds",
          "https://untappd.com/user/genehack"
        ],
        "uid": [
          "https://genehack.org/",
          "https://genehack.org/genehack"
        ],
        "name": [
          "John S Jacobs Anderson"
        ],
        "given-name": [
          "John"
        ],
        "additional-name": [
          "S"
        ],
        "family-name": [
          "Jacobs Anderson"
        ],
        "locality": [
          "Salem"
        ],
        "region": [
          "Oregon"
        ],
        "country-name": [
          "USA"
        ],
        "nickname": [
          "genehack"
        ],
        "pronoun": [
          "https://pronoun.is/he"
        ]
      }
    }
  ],
  "rels": {
    "apple-touch-icon": [
      "https://genehack.org/apple-touch-icon.png?v=1"
    ],
    "icon": [
      "https://genehack.org/favicon-32x32.png?v=1",
      "https://genehack.org/favicon-16x16.png?v=1",
      "https://genehack.org/favicon.ico?v=1"
    ],
    "manifest": [
      "https://genehack.org/site.webmanifest?v=1"
    ],
    "shortcut": [
      "https://genehack.org/favicon.ico?v=1"
    ],
    "stylesheet": [
      "https://genehack.org/css/normalize.css",
      "https://genehack.org/css/site.css"
    ],
    "me": [
      "https://genehack.org/",
      "https://genehack.blog/",
      "https://twitter.com/genehack",
      "https://mastodon.social/@genehack",
      "https://covid.house/",
      "https://recipes.genehack.org/",
      "https://bandcamp.com/genehack",
      "https://metacpan.org/author/GENEHACK",
      "https://diasp.org/people/4d287f11ec26e226f7000384",
      "https://genehack.dreamwidth.org/",
      "https://www.facebook.com/genehack",
      "https://www.flickr.com/photos/genehack/",
      "ircs://chat.freenode.net:6697/genehack,isnick",
      "https://github.com/genehack",
      "https://gitlab.com/genehack",
      "https://www.goodreads.com/user/show/2982810-john-anderson",
      "https://keybase.io/genehack",
      "https://www.instagram.com/genehack/",
      "https://www.linkedin.com/in/johnsjanderson/",
      "https://www.metafilter.com/user/13976",
      "http://genehack.newsblur.com/",
      "https://www.npmjs.com/~genehack",
      "https://opencollective.com/genehack",
      "https://www.patreon.com/genehack/",
      "https://pinboard.in/u:genehack",
      "https://www.pinterest.com/genehack/",
      "https://www.reddit.com/user/genehack/",
      "https://stackexchange.com/users/17710/genehack",
      "https://steamcommunity.com/id/genehack/",
      "https://beta.thestorygraph.com/profile/ff04ef58-368d-4617-9188-727c86bc3228",
      "https://www.tumblr.com/blog/tumblrwds",
      "https://untappd.com/user/genehack"
    ]
  },
  "rel-urls": {
    "https://genehack.org/apple-touch-icon.png?v=1": {
      "rels": [
        "apple-touch-icon"
      ]
    },
    "https://genehack.org/favicon-32x32.png?v=1": {
      "rels": [
        "icon"
      ],
      "type": "image/png"
    },
    "https://genehack.org/favicon-16x16.png?v=1": {
      "rels": [
        "icon"
      ],
      "type": "image/png"
    },
    "https://genehack.org/site.webmanifest?v=1": {
      "rels": [
        "manifest"
      ]
    },
    "https://genehack.org/favicon.ico?v=1": {
      "rels": [
        "icon",
        "shortcut"
      ]
    },
    "https://genehack.org/css/normalize.css": {
      "rels": [
        "stylesheet"
      ]
    },
    "https://genehack.org/css/site.css": {
      "rels": [
        "stylesheet"
      ]
    },
    "https://genehack.org/": {
      "rels": [
        "me"
      ],
      "text": "John S Jacobs Anderson"
    },
    "https://genehack.blog/": {
      "rels": [
        "me"
      ],
      "text": "genehack.blog"
    },
    "https://twitter.com/genehack": {
      "rels": [
        "me"
      ],
      "text": "Twitter"
    },
    "https://mastodon.social/@genehack": {
      "rels": [
        "me"
      ],
      "text": "\n      the Fediverse"
    },
    "https://covid.house/": {
      "rels": [
        "me"
      ],
      "text": "covid.house"
    },
    "https://recipes.genehack.org/": {
      "rels": [
        "me"
      ],
      "text": "\n      recipe site\n    "
    },
    "https://bandcamp.com/genehack": {
      "rels": [
        "me"
      ],
      "text": "\n         bandcamp\n      "
    },
    "https://metacpan.org/author/GENEHACK": {
      "rels": [
        "me"
      ],
      "text": "\n         cpan\n      "
    },
    "https://diasp.org/people/4d287f11ec26e226f7000384": {
      "rels": [
        "me"
      ],
      "text": "\n         diaspora\n      "
    },
    "https://genehack.dreamwidth.org/": {
      "rels": [
        "me"
      ],
      "text": "\n         dreamwidth\n      "
    },
    "https://www.facebook.com/genehack": {
      "rels": [
        "me"
      ],
      "text": "\n         facebook\n      "
    },
    "https://www.flickr.com/photos/genehack/": {
      "rels": [
        "me"
      ],
      "text": "\n         flickr\n      "
    },
    "ircs://chat.freenode.net:6697/genehack,isnick": {
      "rels": [
        "me"
      ],
      "text": "\n         freenode\n      "
    },
    "https://github.com/genehack": {
      "rels": [
        "me"
      ],
      "text": "\n         github\n      "
    },
    "https://gitlab.com/genehack": {
      "rels": [
        "me"
      ],
      "text": "\n         gitlab\n      "
    },
    "https://www.goodreads.com/user/show/2982810-john-anderson": {
      "rels": [
        "me"
      ],
      "text": "\n         goodreads\n      "
    },
    "https://keybase.io/genehack": {
      "rels": [
        "me"
      ],
      "text": "\n         keybase\n      "
    },
    "https://www.instagram.com/genehack/": {
      "rels": [
        "me"
      ],
      "text": "\n         instagram\n      "
    },
    "https://www.linkedin.com/in/johnsjanderson/": {
      "rels": [
        "me"
      ],
      "text": "\n         linkedin\n      "
    },
    "https://www.metafilter.com/user/13976": {
      "rels": [
        "me"
      ],
      "text": "\n         metafilter\n      "
    },
    "http://genehack.newsblur.com/": {
      "rels": [
        "me"
      ],
      "text": "\n         newsblur blurblog\n      "
    },
    "https://www.npmjs.com/~genehack": {
      "rels": [
        "me"
      ],
      "text": "\n         npm\n      "
    },
    "https://opencollective.com/genehack": {
      "rels": [
        "me"
      ],
      "text": " opencollective"
    },
    "https://www.patreon.com/genehack/": {
      "rels": [
        "me"
      ],
      "text": "\n         patreon\n      "
    },
    "https://pinboard.in/u:genehack": {
      "rels": [
        "me"
      ],
      "text": "\n         pinboard\n      "
    },
    "https://www.pinterest.com/genehack/": {
      "rels": [
        "me"
      ],
      "text": "\n         pinterest\n      "
    },
    "https://www.reddit.com/user/genehack/": {
      "rels": [
        "me"
      ],
      "text": "\n         reddit\n      "
    },
    "https://stackexchange.com/users/17710/genehack": {
      "rels": [
        "me"
      ],
      "text": "\n         stack exchange\n      "
    },
    "https://steamcommunity.com/id/genehack/": {
      "rels": [
        "me"
      ],
      "text": "\n         steam\n      "
    },
    "https://beta.thestorygraph.com/profile/ff04ef58-368d-4617-9188-727c86bc3228": {
      "rels": [
        "me"
      ],
      "text": "\n         storygraph\n      "
    },
    "https://www.tumblr.com/blog/tumblrwds": {
      "rels": [
        "me"
      ],
      "text": "\n         tumblr\n      "
    },
    "https://untappd.com/user/genehack": {
      "rels": [
        "me"
      ],
      "text": "\n         untappd\n      "
    }
  }
}