{
  "items": [
    {
      "type": [
        "h-card"
      ],
      "properties": {
        "photo": [
          {
            "value": "https://journal.robbi.my/img/author.png",
            "alt": "Robbi Nespu"
          }
        ],
        "name": [
          "Robbi Nespu"
        ],
        "url": [
          "https://journal.robbi.my/"
        ],
        "pronoun": [
          "https://journal.robbi.my/he / him / his"
        ],
        "email": [
          "mailto:journal@robbi.my"
        ],
        "nickname": [
          "Robbi Nespu"
        ],
        "note": [
          "Hello there! My name is Robbi Nespu. This blog is mostly about my journey on software development / devOps, information security, financial, real estate, property and personal adventures. You can check README for more information."
        ],
        "country-name": [
          "Malaysia"
        ]
      }
    },
    {
      "type": [
        "h-feed"
      ],
      "properties": {},
      "children": [
        {
          "type": [
            "h-entry"
          ],
          "properties": {},
          "children": [
            {
              "type": [
                "h-entry"
              ],
              "properties": {
                "name": [
                  "📝 Django logger (my personal favourite format)"
                ],
                "url": [
                  "https://journal.robbi.my/posts/230309102851/"
                ],
                "published": [
                  "2023-03-09 22:28:51"
                ],
                "category": [
                  "article"
                ]
              }
            }
          ]
        },
        {
          "type": [
            "h-entry"
          ],
          "properties": {},
          "children": [
            {
              "type": [
                "h-entry"
              ],
              "properties": {
                "name": [
                  "📝 Beautify `JSON` on web browser without addons"
                ],
                "url": [
                  "https://journal.robbi.my/posts/230303113521/"
                ],
                "published": [
                  "2023-03-03 23:35:21"
                ],
                "category": [
                  "article"
                ]
              }
            }
          ]
        },
        {
          "type": [
            "h-entry"
          ],
          "properties": {},
          "children": [
            {
              "type": [
                "h-entry"
              ],
              "properties": {
                "name": [
                  "📝 Python 🐍 - active screen cursor movement"
                ],
                "url": [
                  "https://journal.robbi.my/posts/230303011110/"
                ],
                "published": [
                  "2023-03-03 13:11:10"
                ],
                "category": [
                  "article"
                ]
              }
            }
          ]
        },
        {
          "type": [
            "h-entry"
          ],
          "properties": {},
          "children": [
            {
              "type": [
                "h-entry"
              ],
              "properties": {
                "name": [
                  "📝 JOTA 2022 - JOSRAC (Batu Pahat, Johor, Malaysia)"
                ],
                "url": [
                  "https://journal.robbi.my/posts/221014045807/"
                ],
                "published": [
                  "2022-10-14 16:58:07"
                ],
                "category": [
                  "article"
                ]
              }
            }
          ]
        },
        {
          "type": [
            "h-entry"
          ],
          "properties": {},
          "children": [
            {
              "type": [
                "h-entry"
              ],
              "properties": {
                "name": [
                  "📝 JOTA 2021 - JOSRAC (Batu Pahat, Johor, Malaysia)"
                ],
                "url": [
                  "https://journal.robbi.my/posts/211014121028/"
                ],
                "published": [
                  "2021-10-14 12:10:28"
                ],
                "category": [
                  "article"
                ]
              }
            }
          ]
        },
        {
          "type": [
            "h-entry"
          ],
          "properties": {},
          "children": [
            {
              "type": [
                "h-entry"
              ],
              "properties": {
                "name": [
                  "📝 Hugo \"GetJSON\" now support HTTP Header"
                ],
                "url": [
                  "https://journal.robbi.my/posts/211009124047/"
                ],
                "published": [
                  "2021-10-09 12:40:47"
                ],
                "category": [
                  "article"
                ]
              }
            }
          ]
        },
        {
          "type": [
            "h-entry"
          ],
          "properties": {},
          "children": [
            {
              "type": [
                "h-entry"
              ],
              "properties": {
                "name": [
                  "📝 Cawbird - Linux Twitter Client"
                ],
                "url": [
                  "https://journal.robbi.my/posts/210905102438/"
                ],
                "published": [
                  "2021-09-05 22:24:38"
                ],
                "category": [
                  "article"
                ]
              }
            }
          ]
        }
      ]
    }
  ],
  "rels": {
    "canonical": [
      "https://journal.robbi.my/"
    ],
    "alternate": [
      "https://journal.robbi.my/index.xml"
    ],
    "webmention": [
      "https://webmention.io/journal.robbi.my/webmention"
    ],
    "pingback": [
      "https://webmention.io/journal.robbi.my/xmlrpc"
    ],
    "authorization_endpoint": [
      "https://indieauth.com/auth"
    ],
    "token_endpoint": [
      "https://tokens.indieauth.com/token"
    ],
    "microsub": [
      "https://aperture.p3k.io/microsub/810"
    ],
    "micropub": [
      "http://0c2d2c3e.proxy.webhookapp.com/"
    ],
    "stylesheet": [
      "https://journal.robbi.my/custom_style.min.3d0d5fdd9c0747b9bbdca6c3ff42efc6af699158f9a4fca2b686df1b6876addf.css",
      "https://journal.robbi.my/fontawesome/css/fontawesome.min.2b8f23dcda7e255060d49b5b700a867047ea74c765531abe6b92fb3b73e27962.css",
      "https://journal.robbi.my/fontawesome/css/brands.min.7b0bd853b21d24175d629d3d647f7fc97ff0388d6ffb4b2249e457248320a09a.css",
      "https://journal.robbi.my/fontawesome/css/solid.min.9458d04e1734fd1197396a1d271ba626884edf086aedea50faa990bf85c38271.css"
    ],
    "me": [
      "mailto:journal@robbi.my",
      "https://indieweb.social/@robbinespu",
      "https://www.twitter.com/robbinespu",
      "https://fb.me/robbinespu",
      "https://www.tiktok.com/@robbinespu",
      "https://github.com/robbinespu",
      "https://reddit.com/user/robbi_my",
      "https://keybase.io/robbinespu/",
      "mailto:contact@robbi.my"
    ],
    "noopener": [
      "https://indieweb.social/@robbinespu",
      "https://www.twitter.com/robbinespu",
      "https://fb.me/robbinespu",
      "https://www.tiktok.com/@robbinespu",
      "https://github.com/robbinespu",
      "https://reddit.com/user/robbi_my",
      "https://keybase.io/robbinespu/",
      "mailto:contact@robbi.my"
    ],
    "article": [
      "https://journal.robbi.my/posts/230309102851/",
      "https://journal.robbi.my/posts/230303113521/",
      "https://journal.robbi.my/posts/230303011110/",
      "https://journal.robbi.my/posts/221014045807/",
      "https://journal.robbi.my/posts/211014121028/",
      "https://journal.robbi.my/posts/211009124047/",
      "https://journal.robbi.my/posts/210905102438/"
    ]
  },
  "rel-urls": {
    "https://journal.robbi.my/": {
      "rels": [
        "canonical"
      ]
    },
    "https://journal.robbi.my/index.xml": {
      "rels": [
        "alternate"
      ],
      "title": "Journal.robbi.my",
      "type": "application/rss+xml"
    },
    "https://webmention.io/journal.robbi.my/webmention": {
      "rels": [
        "webmention"
      ]
    },
    "https://webmention.io/journal.robbi.my/xmlrpc": {
      "rels": [
        "pingback"
      ]
    },
    "https://indieauth.com/auth": {
      "rels": [
        "authorization_endpoint"
      ]
    },
    "https://tokens.indieauth.com/token": {
      "rels": [
        "token_endpoint"
      ]
    },
    "https://aperture.p3k.io/microsub/810": {
      "rels": [
        "microsub"
      ]
    },
    "http://0c2d2c3e.proxy.webhookapp.com/": {
      "rels": [
        "micropub"
      ]
    },
    "https://journal.robbi.my/custom_style.min.3d0d5fdd9c0747b9bbdca6c3ff42efc6af699158f9a4fca2b686df1b6876addf.css": {
      "rels": [
        "stylesheet"
      ]
    },
    "https://journal.robbi.my/fontawesome/css/fontawesome.min.2b8f23dcda7e255060d49b5b700a867047ea74c765531abe6b92fb3b73e27962.css": {
      "rels": [
        "stylesheet"
      ]
    },
    "https://journal.robbi.my/fontawesome/css/brands.min.7b0bd853b21d24175d629d3d647f7fc97ff0388d6ffb4b2249e457248320a09a.css": {
      "rels": [
        "stylesheet"
      ]
    },
    "https://journal.robbi.my/fontawesome/css/solid.min.9458d04e1734fd1197396a1d271ba626884edf086aedea50faa990bf85c38271.css": {
      "rels": [
        "stylesheet"
      ]
    },
    "mailto:journal@robbi.my": {
      "rels": [
        "me"
      ],
      "text": "Robbi Nespu"
    },
    "https://indieweb.social/@robbinespu": {
      "rels": [
        "me",
        "noopener"
      ]
    },
    "https://www.twitter.com/robbinespu": {
      "rels": [
        "me",
        "noopener"
      ]
    },
    "https://fb.me/robbinespu": {
      "rels": [
        "me",
        "noopener"
      ]
    },
    "https://www.tiktok.com/@robbinespu": {
      "rels": [
        "me",
        "noopener"
      ]
    },
    "https://github.com/robbinespu": {
      "rels": [
        "me",
        "noopener"
      ]
    },
    "https://reddit.com/user/robbi_my": {
      "rels": [
        "me",
        "noopener"
      ]
    },
    "https://keybase.io/robbinespu/": {
      "rels": [
        "me",
        "noopener"
      ]
    },
    "mailto:contact@robbi.my": {
      "rels": [
        "me",
        "noopener"
      ]
    },
    "https://journal.robbi.my/posts/230309102851/": {
      "rels": [
        "article"
      ],
      "text": "https://journal.robbi.my/posts/230309102851/"
    },
    "https://journal.robbi.my/posts/230303113521/": {
      "rels": [
        "article"
      ],
      "text": "https://journal.robbi.my/posts/230303113521/"
    },
    "https://journal.robbi.my/posts/230303011110/": {
      "rels": [
        "article"
      ],
      "text": "https://journal.robbi.my/posts/230303011110/"
    },
    "https://journal.robbi.my/posts/221014045807/": {
      "rels": [
        "article"
      ],
      "text": "https://journal.robbi.my/posts/221014045807/"
    },
    "https://journal.robbi.my/posts/211014121028/": {
      "rels": [
        "article"
      ],
      "text": "https://journal.robbi.my/posts/211014121028/"
    },
    "https://journal.robbi.my/posts/211009124047/": {
      "rels": [
        "article"
      ],
      "text": "https://journal.robbi.my/posts/211009124047/"
    },
    "https://journal.robbi.my/posts/210905102438/": {
      "rels": [
        "article"
      ],
      "text": "https://journal.robbi.my/posts/210905102438/"
    }
  }
}