{
  "items": [
    {
      "type": [
        "h-card"
      ],
      "properties": {}
    }
  ],
  "rels": {
    "me": [
      "https://github.com/mathewi",
      "https://journa.host/@mathewi",
      "http://mathewingram.com/",
      "http://mathewingram.com/cdn-cgi/l/email-protection#8ce1edf8e4e9fbe5e2ebfeede1ccebe1ede5e0a2efe3e1"
    ]
  },
  "rel-urls": {
    "https://github.com/mathewi": {
      "rels": [
        "me"
      ]
    },
    "https://journa.host/@mathewi": {
      "rels": [
        "me"
      ]
    },
    "http://mathewingram.com/": {
      "rels": [
        "me"
      ]
    },
    "http://mathewingram.com/cdn-cgi/l/email-protection#8ce1edf8e4e9fbe5e2ebfeede1ccebe1ede5e0a2efe3e1": {
      "rels": [
        "me"
      ],
      "text": "[email protected]"
    }
  }
}