{
  "items": [],
  "rels": {
    "stylesheet": [
      "http://nullroute.lt/~grawity/style.css"
    ],
    "canonical": [
      "https://nullroute.eu.org/~grawity/"
    ],
    "alternate": [
      "http://nullroute.lt/~grawity/journal.atom"
    ],
    "meta": [
      "http://nullroute.lt/~grawity/foaf.rdf"
    ],
    "vcs-git": [
      "git://git.nullroute.eu.org/grawity/website.git"
    ],
    "license": [
      "https://creativecommons.org/licenses/by/4.0/"
    ],
    "openid.server": [
      "https://login.launchpad.net/+openid"
    ],
    "openid.delegate": [
      "https://login.launchpad.net/+id/EfMfYFm"
    ],
    "openid2.provider": [
      "https://login.launchpad.net/+openid"
    ],
    "openid2.local_id": [
      "https://login.launchpad.net/+id/EfMfYFm"
    ],
    "me": [
      "mailto:grawity@gmail.com"
    ]
  },
  "rel-urls": {
    "http://nullroute.lt/~grawity/style.css": {
      "rels": [
        "stylesheet"
      ]
    },
    "https://nullroute.eu.org/~grawity/": {
      "rels": [
        "canonical"
      ]
    },
    "http://nullroute.lt/~grawity/journal.atom": {
      "rels": [
        "alternate"
      ],
      "type": "application/atom+xml"
    },
    "http://nullroute.lt/~grawity/foaf.rdf": {
      "rels": [
        "meta"
      ],
      "type": "application/rdf+xml"
    },
    "git://git.nullroute.eu.org/grawity/website.git": {
      "rels": [
        "vcs-git"
      ]
    },
    "https://creativecommons.org/licenses/by/4.0/": {
      "rels": [
        "license"
      ]
    },
    "https://login.launchpad.net/+openid": {
      "rels": [
        "openid.server"
      ]
    },
    "https://login.launchpad.net/+id/EfMfYFm": {
      "rels": [
        "openid.delegate"
      ]
    },
    "mailto:grawity@gmail.com": {
      "rels": [
        "me"
      ],
      "text": "email"
    }
  }
}