{
  "items": [
    {
      "type": [
        "h-feed"
      ],
      "properties": {},
      "children": [
        {
          "type": [
            "h-entry"
          ],
          "properties": {
            "name": [
              "Breaking toys"
            ],
            "published": [
              "15 Nov 2022, 9:11 a.m."
            ],
            "content": [
              {
                "html": "<p>Ryan Broderick from Garbage Day on Musk and Twitter.</p>",
                "value": "Ryan Broderick from Garbage Day on Musk and Twitter."
              }
            ]
          }
        },
        {
          "type": [
            "h-entry"
          ],
          "properties": {
            "name": [
              "Site Tinkering"
            ],
            "published": [
              "6 Nov 2022, 10:47 a.m."
            ],
            "content": [
              {
                "html": "<p>Some small changes to the site</p>",
                "value": "Some small changes to the site"
              }
            ]
          }
        },
        {
          "type": [
            "h-entry"
          ],
          "properties": {
            "name": [
              "Shocktober 2022"
            ],
            "published": [
              "17 Oct 2022, 1:36 p.m."
            ],
            "content": [
              {
                "html": "<p>Oxford's premier cult cinema club once again brings their own special brand of entertainment to Halloween.</p>",
                "value": "Oxford's premier cult cinema club once again brings their own special brand of entertainment to Halloween."
              }
            ]
          }
        }
      ]
    },
    {
      "type": [
        "h-feed"
      ],
      "properties": {},
      "children": [
        {
          "type": [
            "h-entry"
          ],
          "properties": {
            "name": [
              "Mastodon on your own domain without hosting a server"
            ],
            "published": [
              "16 Nov 2022, 7:54 p.m."
            ],
            "content": [
              {
                "html": "“However, there is one thing I would like my own server for: discoverability. Much like with e-mail, I want folks to have an easy address to find me, and one that I can keep giving out to everyone even if later I switch to a different Mastodon server. A bit like e-mail forwarding to your ISP’s e-mail service.\n\nThe good news is: you can use your own domain and share it with other folks. It will link to your actual account.”",
                "value": "“However, there is one thing I would like my own server for: discoverability. Much like with e-mail, I want folks to have an easy address to find me, and one that I can keep giving out to everyone even if later I switch to a different Mastodon server. A bit like e-mail forwarding to your ISP’s e-mail service.\n\nThe good news is: you can use your own domain and share it with other folks. It will link to your actual account.”"
              }
            ]
          }
        },
        {
          "type": [
            "h-entry"
          ],
          "properties": {
            "name": [
              "Responsive Animations for Every Screen Size and Device"
            ],
            "published": [
              "16 Nov 2022, 7:48 p.m."
            ],
            "content": [
              {
                "html": "",
                "value": ""
              }
            ]
          }
        },
        {
          "type": [
            "h-entry"
          ],
          "properties": {
            "name": [
              "Brands Town"
            ],
            "published": [
              "16 Nov 2022, 11:30 a.m."
            ],
            "content": [
              {
                "html": "“Brands Town is the first ever Mastodon Instance dedicated solely to corporate brand promotion.”",
                "value": "“Brands Town is the first ever Mastodon Instance dedicated solely to corporate brand promotion.”"
              }
            ]
          }
        },
        {
          "type": [
            "h-entry"
          ],
          "properties": {
            "name": [
              "the Movie title stills collection"
            ],
            "published": [
              "14 Nov 2022, 9:50 a.m."
            ],
            "content": [
              {
                "html": "\"This is the world’s largest online archive dedicated to the evolution of title sequence design in cinema, featuring stills and videos from title sequences of 5,797 feature films from 1902 to 2022. View individual titles, or see them displayed side by side on one of the 400 pages featuring studios, genres, designers, directors and actors.\"",
                "value": "\"This is the world’s largest online archive dedicated to the evolution of title sequence design in cinema, featuring stills and videos from title sequences of 5,797 feature films from 1902 to 2022. View individual titles, or see them displayed side by side on one of the 400 pages featuring studios, genres, designers, directors and actors.\""
              }
            ]
          }
        },
        {
          "type": [
            "h-entry"
          ],
          "properties": {
            "name": [
              "ShellCheck"
            ],
            "published": [
              "13 Nov 2022, 11:37 p.m."
            ],
            "content": [
              {
                "html": "Finds bugs in shell scripts, installable via homebrew.",
                "value": "Finds bugs in shell scripts, installable via homebrew."
              }
            ]
          }
        }
      ]
    }
  ],
  "rels": {
    "canonical": [
      "https://polytechnic.co.uk/"
    ],
    "stylesheet": [
      "https://polytechnic.co.uk/static/main.031c0955c849.css"
    ],
    "apple-touch-icon": [
      "https://polytechnic.co.uk/static/apple-touch-icon.e4a9e9b4f232.png"
    ],
    "icon": [
      "https://polytechnic.co.uk/static/favicon-32x32.72fb5ce64ca7.png",
      "https://polytechnic.co.uk/static/favicon-16x16.efc15992dc4a.png"
    ],
    "manifest": [
      "https://polytechnic.co.uk/static/manifest.407143223143.json"
    ],
    "mask-icon": [
      "https://polytechnic.co.uk/static/safari-pinned-tab.2d47b1d17534.svg"
    ],
    "me": [
      "mailto:garrettc@polytechnic.co.uk",
      "https://twitter.com/garrettc",
      "https://flickr.com/people/garrettc",
      "https://pinboard.in/u:garrettc",
      "https://mastodon.org.uk/@garrettc",
      "https://www.last.fm/user/garrettc",
      "https://www.goodreads.com/garrettc",
      "https://letterboxd.com/garrettc/",
      "https://github.com/garrettc",
      "https://uk.linkedin.com/in/garrettc/"
    ],
    "authorization_endpoint": [
      "https://indieauth.com/auth"
    ],
    "alternate": [
      "https://polytechnic.co.uk/blog/rss"
    ],
    "license": [
      "http://creativecommons.org/licenses/by-nc-sa/4.0/"
    ],
    "cc:attributionURL": [
      "https://polytechnic.co.uk/"
    ]
  },
  "rel-urls": {
    "https://polytechnic.co.uk/": {
      "rels": [
        "canonical"
      ]
    },
    "https://polytechnic.co.uk/static/main.031c0955c849.css": {
      "rels": [
        "stylesheet"
      ],
      "type": "text/css"
    },
    "https://polytechnic.co.uk/static/apple-touch-icon.e4a9e9b4f232.png": {
      "rels": [
        "apple-touch-icon"
      ]
    },
    "https://polytechnic.co.uk/static/favicon-32x32.72fb5ce64ca7.png": {
      "rels": [
        "icon"
      ],
      "type": "image/png"
    },
    "https://polytechnic.co.uk/static/favicon-16x16.efc15992dc4a.png": {
      "rels": [
        "icon"
      ],
      "type": "image/png"
    },
    "https://polytechnic.co.uk/static/manifest.407143223143.json": {
      "rels": [
        "manifest"
      ]
    },
    "https://polytechnic.co.uk/static/safari-pinned-tab.2d47b1d17534.svg": {
      "rels": [
        "mask-icon"
      ]
    },
    "mailto:garrettc@polytechnic.co.uk": {
      "rels": [
        "me"
      ]
    },
    "https://twitter.com/garrettc": {
      "rels": [
        "me"
      ]
    },
    "https://indieauth.com/auth": {
      "rels": [
        "authorization_endpoint"
      ]
    },
    "https://polytechnic.co.uk/blog/rss": {
      "rels": [
        "alternate"
      ],
      "title": "Blog RSS",
      "type": "application/rss+xml"
    },
    "https://flickr.com/people/garrettc": {
      "rels": [
        "me"
      ],
      "text": "View all photos on Flickr"
    },
    "https://pinboard.in/u:garrettc": {
      "rels": [
        "me"
      ],
      "text": "More bookmarks on Pinboard"
    },
    "https://mastodon.org.uk/@garrettc": {
      "rels": [
        "me"
      ],
      "text": "Mastodon"
    },
    "https://www.last.fm/user/garrettc": {
      "rels": [
        "me"
      ],
      "text": "Last.fm"
    },
    "https://www.goodreads.com/garrettc": {
      "rels": [
        "me"
      ],
      "text": "GoodReads"
    },
    "https://letterboxd.com/garrettc/": {
      "rels": [
        "me"
      ],
      "text": "Letterboxd"
    },
    "https://github.com/garrettc": {
      "rels": [
        "me"
      ],
      "text": "GitHub"
    },
    "https://uk.linkedin.com/in/garrettc/": {
      "rels": [
        "me"
      ],
      "text": "LinkedIn"
    },
    "http://creativecommons.org/licenses/by-nc-sa/4.0/": {
      "rels": [
        "license"
      ],
      "text": "Polytechnic"
    }
  }
}