{
  "items": [],
  "rels": {
    "alternate": [
      "https://andigalpern.com/feed/",
      "https://andigalpern.com/comments/feed/"
    ],
    "stylesheet": [
      "http://andigalpern.com/wp-includes/css/dist/block-library/style.min.css?ver=6.1.1",
      "http://andigalpern.com/wp-includes/css/classic-themes.min.css?ver=1",
      "http://andigalpern.com/wp-includes/css/dashicons.min.css?ver=6.1.1",
      "http://andigalpern.com/wp-content/plugins/post-views-counter/css/frontend.min.css?ver=1.3.12",
      "http://andigalpern.com/wp-content/themes/generatepress/assets/css/main.min.css?ver=3.2.4"
    ],
    "https://api.w.org/": [
      "https://andigalpern.com/wp-json/"
    ],
    "EditURI": [
      "http://andigalpern.com/xmlrpc.php?rsd"
    ],
    "wlwmanifest": [
      "http://andigalpern.com/wp-includes/wlwmanifest.xml"
    ],
    "bookmark": [
      "https://andigalpern.com/2023/03/06/3010/",
      "https://andigalpern.com/2023/03/06/3008/",
      "https://andigalpern.com/2023/03/06/3006/",
      "https://andigalpern.com/2023/03/06/3003/",
      "https://andigalpern.com/2023/03/06/3000/",
      "https://andigalpern.com/2023/03/06/2997/",
      "https://andigalpern.com/2023/03/05/2987/",
      "https://andigalpern.com/2023/03/05/2976/",
      "https://andigalpern.com/2023/03/05/2973/",
      "https://andigalpern.com/2023/03/05/2971/"
    ],
    "author": [
      "https://andigalpern.com/author/ndu/"
    ],
    "category": [
      "https://andigalpern.com/category/sw/",
      "https://andigalpern.com/category/uncategorized/",
      "https://andigalpern.com/category/90-day/",
      "https://andigalpern.com/category/gh/",
      "https://andigalpern.com/category/ckb/"
    ],
    "tag": [
      "https://andigalpern.com/category/sw/",
      "https://andigalpern.com/category/uncategorized/",
      "https://andigalpern.com/category/90-day/",
      "https://andigalpern.com/category/gh/",
      "https://andigalpern.com/category/ckb/"
    ]
  },
  "rel-urls": {
    "https://andigalpern.com/feed/": {
      "rels": [
        "alternate"
      ],
      "title": "» Feed",
      "type": "application/rss+xml"
    },
    "https://andigalpern.com/comments/feed/": {
      "rels": [
        "alternate"
      ],
      "title": "» Comments Feed",
      "type": "application/rss+xml"
    },
    "http://andigalpern.com/wp-includes/css/dist/block-library/style.min.css?ver=6.1.1": {
      "rels": [
        "stylesheet"
      ],
      "media": "all"
    },
    "http://andigalpern.com/wp-includes/css/classic-themes.min.css?ver=1": {
      "rels": [
        "stylesheet"
      ],
      "media": "all"
    },
    "http://andigalpern.com/wp-includes/css/dashicons.min.css?ver=6.1.1": {
      "rels": [
        "stylesheet"
      ],
      "media": "all"
    },
    "http://andigalpern.com/wp-content/plugins/post-views-counter/css/frontend.min.css?ver=1.3.12": {
      "rels": [
        "stylesheet"
      ],
      "media": "all"
    },
    "http://andigalpern.com/wp-content/themes/generatepress/assets/css/main.min.css?ver=3.2.4": {
      "rels": [
        "stylesheet"
      ],
      "media": "all"
    },
    "https://andigalpern.com/wp-json/": {
      "rels": [
        "https://api.w.org/"
      ]
    },
    "http://andigalpern.com/xmlrpc.php?rsd": {
      "rels": [
        "EditURI"
      ],
      "title": "RSD",
      "type": "application/rsd+xml"
    },
    "http://andigalpern.com/wp-includes/wlwmanifest.xml": {
      "rels": [
        "wlwmanifest"
      ],
      "type": "application/wlwmanifest+xml"
    },
    "https://andigalpern.com/2023/03/06/3010/": {
      "rels": [
        "bookmark"
      ],
      "text": "How Christine Brown Is Embracing Life With Boyfriend David"
    },
    "https://andigalpern.com/author/ndu/": {
      "rels": [
        "author"
      ],
      "title": "View all posts by ndu",
      "text": "ndu"
    },
    "https://andigalpern.com/category/sw/": {
      "rels": [
        "category",
        "tag"
      ],
      "text": "SW"
    },
    "https://andigalpern.com/2023/03/06/3008/": {
      "rels": [
        "bookmark"
      ],
      "text": "aaaa"
    },
    "https://andigalpern.com/category/uncategorized/": {
      "rels": [
        "category",
        "tag"
      ],
      "text": "Uncategorized"
    },
    "https://andigalpern.com/2023/03/06/3006/": {
      "rels": [
        "bookmark"
      ],
      "text": "Sister Wives’ Gwendlyn Brown Breaks Silence on Mom Christine’s Boyfriend David Woolley in Video"
    },
    "https://andigalpern.com/2023/03/06/3003/": {
      "rels": [
        "bookmark"
      ],
      "text": "Jenny & Sumit Surprise Fans By Joining Another 90 Day Fiancé Spin-Off"
    },
    "https://andigalpern.com/category/90-day/": {
      "rels": [
        "category",
        "tag"
      ],
      "text": "90 Day"
    },
    "https://andigalpern.com/2023/03/06/3000/": {
      "rels": [
        "bookmark"
      ],
      "text": "General Hospital Update: Monday, March 6 – Liesl’s Plea to Willow – Sonny’s Reasons To Celebrate – Spencer Loses To Esme"
    },
    "https://andigalpern.com/category/gh/": {
      "rels": [
        "category",
        "tag"
      ],
      "text": "GH"
    },
    "https://andigalpern.com/2023/03/06/2997/": {
      "rels": [
        "bookmark"
      ],
      "text": "Travis Kelce Supported by Brother Jason and Parents Donna and Ed During His ‘SNL’ Hosting Debut"
    },
    "https://andigalpern.com/2023/03/05/2987/": {
      "rels": [
        "bookmark"
      ],
      "text": "Todd Chrisley ɢᴀʏ CELEBRITY Is Todd Chrisley ɢᴀʏ ? Rumor Or Reality-Chrisley Maintains Innocence Amid Bank ғʀᴀᴜᴅ Accusations!"
    },
    "https://andigalpern.com/category/ckb/": {
      "rels": [
        "category",
        "tag"
      ],
      "text": "CKB"
    },
    "https://andigalpern.com/2023/03/05/2976/": {
      "rels": [
        "bookmark"
      ],
      "text": "‘Sister Wives’ See Inside Kody & Robyn Brown’s $1M Lavish Home"
    },
    "https://andigalpern.com/2023/03/05/2973/": {
      "rels": [
        "bookmark"
      ],
      "text": "Chris Rock Skewers Will and Jada Pinkett Smith Entanglement Drama: ‘She Hurt Him Way More Than He Hurt Me’"
    },
    "https://andigalpern.com/2023/03/05/2971/": {
      "rels": [
        "bookmark"
      ],
      "text": "General Hospital Spoilers: GH March Preview – Port Charles Faces Sad Goodbye – Sonny in Danger – Wedding Day Drama"
    }
  }
}